MANIFEST.in
README.md
setup.cfg
setup.py
Kodi_Voice.egg-info/PKG-INFO
Kodi_Voice.egg-info/SOURCES.txt
Kodi_Voice.egg-info/dependency_links.txt
Kodi_Voice.egg-info/not-zip-safe
Kodi_Voice.egg-info/requires.txt
Kodi_Voice.egg-info/top_level.txt
kodi_voice/ISO-639-2_utf-8.txt
kodi_voice/NUMWORDS.de.txt
kodi_voice/NUMWORDS.en.txt
kodi_voice/NUMWORDS.it.txt
kodi_voice/__init__.py
kodi_voice/cache.py
kodi_voice/kodi.config.example
kodi_voice/kodi.py