Metadata-Version: 1.0
Name: Kodi-Voice
Version: 1.1.4
Summary: A library for interfacing with Kodi with VUI platforms like Amazon Alexa, Google Home, and Cortana.
Home-page: https://github.com/m0ngr31/kodi-voice
Author: Joe Ipson
Author-email: joe@ipson.me
License: UNKNOWN
Keywords: kodi,voice,alexa
Platform: UNKNOWN
